dcdataset/__init__.py
dcdataset/test.py
dcdataset/utils.py
dcdataset/datasets/__init__.py
dcdataset/datasets/cifar10.py
dcdataset/datasets/imdb_review.py
dcdataset/datasets/squad11.py
dcdataset-0.0.3.dist-info/METADATA
dcdataset-0.0.3.dist-info/WHEEL
dcdataset-0.0.3.dist-info/top_level.txt
dcdataset-0.0.3.dist-info/RECORD
