Metadata-Version: 2.1
Name: dcdataset
Version: 0.0.3
Summary: DeepCluster dataset service package
Home-page: UNKNOWN
Author: YL & SW
Author-email: deepcluster.io@gmail.com
License: UNKNOWN
Platform: UNKNOWN
Classifier: Programming Language :: Python :: 3
Classifier: Operating System :: OS Independent
Requires-Dist: urllib3
Requires-Dist: six
